pyoura/__init__.py
pyoura/__main__.py
pyoura/spinners.py
pyoura-0.1.7.dist-info/METADATA
pyoura-0.1.7.dist-info/WHEEL
pyoura-0.1.7.dist-info/entry_points.txt
pyoura-0.1.7.dist-info/top_level.txt
pyoura-0.1.7.dist-info/RECORD
