Metadata-Version: 2.1
Name: pyoura
Version: 0.1.7
Summary: A Python library for creating command-line spinners
Author: Jack
Author-email: kinginjack@gmail.com
Classifier: Programming Language :: Python :: 3
Classifier: License :: OSI Approved :: MIT License
Classifier: Operating System :: OS Independent
Requires-Python: >=3.6
